cloudbase_agent/__init__.py
cloudbase_agent/langchain/__init__.py
cloudbase_agent/langchain/chat_history.py
cloudbase_agent/langchain/store/__init__.py
cloudbase_agent/langchain/store/tdai.py
cloudbase_agent/langgraph/__init__.py
cloudbase_agent/langgraph/ag_ui_langgraph_patch.py
cloudbase_agent/langgraph/agent.py
cloudbase_agent/langgraph/checkpoint.py
cloudbase_agent/langgraph/util.py
cloudbase_agent/langgraph/store/__init__.py
cloudbase_agent/langgraph/store/tdai_store.py
cloudbase_agent_langgraph-0.1.10.dist-info/METADATA
cloudbase_agent_langgraph-0.1.10.dist-info/WHEEL
cloudbase_agent_langgraph-0.1.10.dist-info/RECORD
